datafact/__about__.py
datafact/__init__.py
datafact/cli.py
datafact/proj.py
datafact/subcmd/__init__.py
datafact/subcmd/build.py
datafact/subcmd/experimental.py
datafact/subcmd/init.py
datafact/subcmd/preview.py
datafact/subcmd/publish.py
datafact/subcmd/templates.py
datafact/subcmd/upgrade.py
datafact/templates/__init__.py
datafact/templates/items.py
datafact/templates/common/__init__.py
datafact/templates/common/bin_files_false.py.jinja2
datafact/templates/common/bin_files_true.py.jinja2
datafact/templates/common/gitignore.jinja2
datafact/templates/common/project.py.jinja2
datafact/templates/crawler/__init__.py
datafact/templates/helloworld/README.md.jinja2
datafact/templates/helloworld/__init__.py
datafact/templates/helloworld/data.py.jinja2
datafact/templates/helloworld/type.py.jinja2
datafact/templates/media/README.md.jinja2
datafact/templates/media/__init__.py
datafact/templates/media/data.py.jinja2
datafact/templates/media/type.py.jinja2
datafact/templates/synthetic/README.md.jinja2
datafact/templates/synthetic/__init__.py
datafact/templates/synthetic/data.py.jinja2
datafact/templates/synthetic/fn.py.jinja2
datafact/templates/synthetic/type.py.jinja2
datafact-0.0.13.dist-info/METADATA
datafact-0.0.13.dist-info/WHEEL
datafact-0.0.13.dist-info/entry_points.txt
datafact-0.0.13.dist-info/licenses/LICENSE.txt
datafact-0.0.13.dist-info/RECORD
